{"type":"FeatureCollection", "features": [
{"type":"Feature","geometry":{"type":"Point","coordinates":[-8.418040054635602,40.33500319021527]},"properties":{"NO_1":240,"Folio":"9","Top_Orig":"Apampilhosa","Lat_Orig":"40º50","Long_Orig":"1º22,5","Álvaro_Se":"IX,36","Top_SD":"Pampilhosa","Lat_SD":"40º20","Long_SD":"8º24","Top_Atual":"Pampilhosa do Botão","Obs_VDigit":"","Distrito":"Aveiro","Concelho":"Mealhada","Freguesia":"Pampilhosa"}},
{"type":"Feature","geometry":{"type":"Point","coordinates":[-8.476729426238336,40.37132716205966]},"properties":{"NO_1":241,"Folio":"9v","Top_Orig":"Apedrulha","Lat_Orig":"40º46,66","Long_Orig":"1º21","Álvaro_Se":"IX,33","Top_SD":"Pedrulha","Lat_SD":"40º22","Long_SD":"8º27","Top_Atual":"Pedrulha","Obs_VDigit":"","Distrito":"Aveiro","Concelho":"Mealhada","Freguesia":"Casal Comba"}},
{"type":"Feature","geometry":{"type":"Point","coordinates":[-8.468111298978698,40.366699889629615]},"properties":{"NO_1":483,"Folio":"17","Top_Orig":"CaSalcoba","Lat_Orig":"40º52,5","Long_Orig":"1º20","Álvaro_Se":"--","Top_SD":"Casal Comba","Lat_SD":"40º22","Long_SD":"8º27","Top_Atual":"Casal Comba","Obs_VDigit":"","Distrito":"Aveiro","Concelho":"Mealhada","Freguesia":"Casal Comba"}},
{"type":"Feature","geometry":{"type":"Point","coordinates":[-8.45141501196747,40.378071897102274]},"properties":{"NO_1":239,"Folio":"9","Top_Orig":"Amealhada","Lat_Orig":"40º52,5","Long_Orig":"1º21","Álvaro_Se":"IX,37","Top_SD":"Mealhada","Lat_SD":"40º22","Long_SD":"8º26","Top_Atual":"Mealhada","Obs_VDigit":"","Distrito":"Aveiro","Concelho":"Mealhada","Freguesia":"Mealhada"}},
{"type":"Feature","geometry":{"type":"Point","coordinates":[-8.47506628870868,40.38317925784056]},"properties":{"NO_1":318,"Folio":"11v","Top_Orig":"Amtes","Lat_Orig":"40º54","Long_Orig":"1º18","Álvaro_Se":"--","Top_SD":"Antes","Lat_SD":"40º22","Long_SD":"8º27","Top_Atual":"Antes","Obs_VDigit":"","Distrito":"Aveiro","Concelho":"Mealhada","Freguesia":"Antes"}},
{"type":"Feature","geometry":{"type":"Point","coordinates":[-8.435077423062872,40.440271244273305]},"properties":{"NO_1":234,"Folio":"9","Top_Orig":"Anadia","Lat_Orig":"41º00","Long_Orig":"1º25","Álvaro_Se":"IX,42","Top_SD":"Anadia","Lat_SD":"40º26","Long_SD":"8º25","Top_Atual":"Anadia","Obs_VDigit":"","Distrito":"Aveiro","Concelho":"Anadia","Freguesia":"Arcos"}},
{"type":"Feature","geometry":{"type":"Point","coordinates":[-8.417515446148283,40.447672316448916]},"properties":{"NO_1":479,"Folio":"17","Top_Orig":"Carualhaes","Lat_Orig":"41º00","Long_Orig":"1º25","Álvaro_Se":"--","Top_SD":"Carvalhais","Lat_SD":"40º26","Long_SD":"8º25","Top_Atual":"Carvalhais","Obs_VDigit":"","Distrito":"Aveiro","Concelho":"Anadia","Freguesia":"Moita"}},
{"type":"Feature","geometry":{"type":"Point","coordinates":[-8.44863444593058,40.45271659416246]},"properties":{"NO_1":647,"Folio":"22","Top_Orig":"Famyluicam","Lat_Orig":"41º00","Long_Orig":"1º18","Álvaro_Se":"IX,41","Top_SD":"Famalicão (Arcos)","Lat_SD":"40º26","Long_SD":"8º27","Top_Atual":"Famalicão","Obs_VDigit":"","Distrito":"Aveiro","Concelho":"Anadia","Freguesia":"Arcos"}},
{"type":"Feature","geometry":{"type":"Point","coordinates":[-8.453586727626876,40.47990913204273]},"properties":{"NO_1":238,"Folio":"9","Top_Orig":"Auelasdecaminho","Lat_Orig":"41º00","Long_Orig":"1º22,5","Álvaro_Se":"IX,43","Top_SD":"Avelãs de Caminho","Lat_SD":"40º28","Long_SD":"8º26","Top_Atual":"Avelãs de Caminho","Obs_VDigit":"","Distrito":"Aveiro","Concelho":"Anadia","Freguesia":"Avelãs de Caminho"}},
{"type":"Feature","geometry":{"type":"Point","coordinates":[-8.416421318021204,40.48247074439512]},"properties":{"NO_1":233,"Folio":"9","Top_Orig":"Auelasdeçima","Lat_Orig":"41º00","Long_Orig":"1º19,5","Álvaro_Se":"IX,44","Top_SD":"Avelãs de Cima","Lat_SD":"40º28","Long_SD":"8º24","Top_Atual":"Avelãs de Cima","Obs_VDigit":"","Distrito":"Aveiro","Concelho":"Anadia","Freguesia":"Avelãs de Cima"}},
{"type":"Feature","geometry":{"type":"Point","coordinates":[-8.504618190309872,40.46618064217909]},"properties":{"NO_1":169,"Folio":"7","Top_Orig":"Ancas","Lat_Orig":"41º01","Long_Orig":"1º20","Álvaro_Se":"IX,23","Top_SD":"Ancas (Anadia)","Lat_SD":"40º27","Long_SD":"8º30","Top_Atual":"Ancas","Obs_VDigit":"","Distrito":"Aveiro","Concelho":"Anadia","Freguesia":"Ancas"}},
{"type":"Feature","geometry":{"type":"Point","coordinates":[-8.46231723013791,40.45173100662076]},"properties":{"NO_1":825,"Folio":"28","Top_Orig":"Mogofores","Lat_Orig":"40º57,5","Long_Orig":"1º21","Álvaro_Se":"--","Top_SD":"Mogofores","Lat_SD":"40º26","Long_SD":"8º27","Top_Atual":"Mogofores","Obs_VDigit":"","Distrito":"Aveiro","Concelho":"Anadia","Freguesia":"Mogofores"}},
{"type":"Feature","geometry":{"type":"Point","coordinates":[-8.578107331517886,40.48331852019298]},"properties":{"NO_1":795,"Folio":"27","Top_Orig":"Mamores","Lat_Orig":"41º00","Long_Orig":"1º16,5","Álvaro_Se":"IX,22","Top_SD":"Marmarrosa","Lat_SD":"40º28","Long_SD":"8º34","Top_Atual":"Marmarrosa","Obs_VDigit":"","Distrito":"Aveiro","Concelho":"Oliveira do Bairro","Freguesia":"Mamarrosa"}},
{"type":"Feature","geometry":{"type":"Point","coordinates":[-8.555795739240816,40.45750905239184]},"properties":{"NO_1":391,"Folio":"14","Top_Orig":"Bemfica","Lat_Orig":"40º56","Long_Orig":"1º18","Álvaro_Se":"--","Top_SD":"Bemposta","Lat_SD":"40º27","Long_SD":"8º32","Top_Atual":"Bemposta","Obs_VDigit":"","Distrito":"Aveiro","Concelho":"Anadia","Freguesia":"Vilarinho do Bairro"}},
{"type":"Feature","geometry":{"type":"Point","coordinates":[-8.546908272508842,40.45265514809895]},"properties":{"NO_1":746,"Folio":"25v","Top_Orig":"Leuira","Lat_Orig":"41º00","Long_Orig":"1º18","Álvaro_Se":"--","Top_SD":"Levira","Lat_SD":"40º26","Long_SD":"8º32","Top_Atual":"Levira","Obs_VDigit":"","Distrito":"Aveiro","Concelho":"Anadia","Freguesia":"São Lourenço do Bairro"}},
{"type":"Feature","geometry":{"type":"Point","coordinates":[-8.163973102559293,40.96954450681412]},"properties":{"NO_1":313,"Folio":"11v","Top_Orig":"Aluaremga","Lat_Orig":"41º25","Long_Orig":"1º51","Álvaro_Se":"VII,38","Top_SD":"Alvarenga (Arouca)","Lat_SD":"40º58","Long_SD":"8º09","Top_Atual":"Alvarenga","Obs_VDigit":"","Distrito":"Aveiro","Concelho":"Arouca","Freguesia":"Alvarenga"}},
{"type":"Feature","geometry":{"type":"Point","coordinates":[-8.270465909676457,40.97777995126318]},"properties":{"NO_1":972,"Folio":"32v","Top_Orig":"Oxeyxo","Lat_Orig":"41º34","Long_Orig":"1º50","Álvaro_Se":"VII,33","Top_SD":"Seixo (Real)","Lat_SD":"40º58","Long_SD":"8º15","Top_Atual":"Seixo","Obs_VDigit":"","Distrito":"Aveiro","Concelho":"Castelo de Paiva","Freguesia":"Real"}},
{"type":"Feature","geometry":{"type":"Point","coordinates":[-8.31878442955895,40.98406655790748]},"properties":{"NO_1":709,"Folio":"24","Top_Orig":"Gomdrra","Lat_Orig":"--","Long_Orig":"--","Álvaro_Se":"--","Top_SD":"Gondra","Lat_SD":"40º58","Long_SD":"8º19","Top_Atual":"Gondra","Obs_VDigit":"","Distrito":"Aveiro","Concelho":"Castelo de Paiva","Freguesia":"Paraíso"}},
{"type":"Feature","geometry":{"type":"Point","coordinates":[-8.337505288074997,40.93814363831638]},"properties":{"NO_1":482,"Folio":"17","Top_Orig":"Carualhall","Lat_Orig":"41º30","Long_Orig":"1º40","Álvaro_Se":"VII,25","Top_SD":"Carvalhal (Tropeço)","Lat_SD":"40º56","Long_SD":"8º20","Top_Atual":"Carvalhal","Obs_VDigit":"","Distrito":"Aveiro","Concelho":"Arouca","Freguesia":"Tropeço"}},
{"type":"Feature","geometry":{"type":"Point","coordinates":[-8.24830738960602,40.95760879105845]},"properties":{"NO_1":828,"Folio":"28","Top_Orig":"Macam","Lat_Orig":"41º30","Long_Orig":"1º46","Álvaro_Se":"VII,28","Top_SD":"Moção (Santa Eulália)","Lat_SD":"40º57","Long_SD":"8º14","Top_Atual":"Monte Moção","Obs_VDigit":"","Distrito":"Aveiro","Concelho":"Arouca","Freguesia":"Santa Eulália"}},
{"type":"Feature","geometry":{"type":"Point","coordinates":[-8.24630140043213,40.9285622938043]},"properties":{"NO_1":262,"Folio":"10","Top_Orig":"Arouca","Lat_Orig":"41º28","Long_Orig":"1º48","Álvaro_Se":"VII,32","Top_SD":"Arouca","Lat_SD":"40º55","Long_SD":"8º14","Top_Atual":"Arouca","Obs_VDigit":"","Distrito":"Aveiro","Concelho":"Arouca","Freguesia":"Arouca"}},
{"type":"Feature","geometry":{"type":"Point","coordinates":[-8.255603013646722,40.89677126453787]},"properties":{"NO_1":285,"Folio":"10v","Top_Orig":"Agramya","Lat_Orig":"41º25","Long_Orig":"1º46","Álvaro_Se":"VII,31","Top_SD":"Granja (Moldes)","Lat_SD":"40º53","Long_SD":"8º15","Top_Atual":"Granja","Obs_VDigit":"","Distrito":"Aveiro","Concelho":"Arouca","Freguesia":"Moldes"}},
{"type":"Feature","geometry":{"type":"Point","coordinates":[-8.27513352427029,40.86827850954956]},"properties":{"NO_1":273,"Folio":"10v","Top_Orig":"Albergaria","Lat_Orig":"41º22,5","Long_Orig":"1º45","Álvaro_Se":"VII,26","Top_SD":"Albergaria das Cabras","Lat_SD":"40º52","Long_SD":"8º16","Top_Atual":"Albergaria da Serra","Obs_VDigit":"","Distrito":"Aveiro","Concelho":"Arouca","Freguesia":"Albergaria da Serra"}},
{"type":"Feature","geometry":{"type":"Point","coordinates":[-8.165830671342198,40.88344351283202]},"properties":{"NO_1":537,"Folio":"18v","Top_Orig":"Cobelo","Lat_Orig":"41º18","Long_Orig":"1º48,75","Álvaro_Se":"VII,37","Top_SD":"Covelo do Paivo","Lat_SD":"40º53","Long_SD":"8º12","Top_Atual":"Covelo de Paivô","Obs_VDigit":"","Distrito":"Aveiro","Concelho":"Arouca","Freguesia":"Covelo de Paivó"}},
{"type":"Feature","geometry":{"type":"Point","coordinates":[-8.487190111039277,40.98510569903098]},"properties":{"NO_1":751,"Folio":"25v","Top_Orig":"Lobam","Lat_Orig":"41º32,5","Long_Orig":"1º32","Álvaro_Se":"VII,21","Top_SD":"Lobão (Feira)","Lat_SD":"40º59","Long_SD":"8º29","Top_Atual":"Lobão","Obs_VDigit":"","Distrito":"Aveiro","Concelho":"Santa Maria da Feira","Freguesia":"Lobão"}},
{"type":"Feature","geometry":{"type":"Point","coordinates":[-8.458838917424497,40.98004357866901]},"properties":{"NO_1":745,"Folio":"25v","Top_Orig":"Louredo","Lat_Orig":"41º32","Long_Orig":"0º35,62","Álvaro_Se":"VII,19","Top_SD":"Louredo (Feira)","Lat_SD":"40º58","Long_SD":"8º27","Top_Atual":"Louredo","Obs_VDigit":"","Distrito":"Aveiro","Concelho":"Santa Maria da Feira","Freguesia":"Louredo"}},
{"type":"Feature","geometry":{"type":"Point","coordinates":[-8.522969902427523,40.964191688418495]},"properties":{"NO_1":953,"Folio":"32","Top_Orig":"OSoutoRedomdo","Lat_Orig":"41º31","Long_Orig":"1º30","Álvaro_Se":"VII,14","Top_SD":"Souto Redondo","Lat_SD":"40º57","Long_SD":"8º33","Top_Atual":"Souto Redondo","Obs_VDigit":"","Distrito":"Aveiro","Concelho":"Santa Maria da Feira","Freguesia":"São João de Ver"}},
{"type":"Feature","geometry":{"type":"Point","coordinates":[-8.547566243962116,40.925801258081094]},"properties":{"NO_1":547,"Folio":"19","Top_Orig":"ConSelhodeferos","Lat_Orig":"41º39","Long_Orig":"1º35","Álvaro_Se":"--","Top_SD":"Feira","Lat_SD":"40º55","Long_SD":"8º32","Top_Atual":"Santa Maria da Feira","Obs_VDigit":"","Distrito":"Aveiro","Concelho":"Santa Maria da Feira","Freguesia":"Feira"}},
{"type":"Feature","geometry":{"type":"Point","coordinates":[-8.494150555203335,40.91225441773233]},"properties":{"NO_1":269,"Folio":"10","Top_Orig":"Arifanadesantama","Lat_Orig":"41º27","Long_Orig":"1º15","Álvaro_Se":"VII,13","Top_SD":"Arrifana (Feira)","Lat_SD":"40º54","Long_SD":"8º29","Top_Atual":"Arrifana","Obs_VDigit":"","Distrito":"Aveiro","Concelho":"Santa Maria da Feira","Freguesia":"Arrifana"}},
{"type":"Feature","geometry":{"type":"Point","coordinates":[-8.597285693572495,40.86106139568163]},"properties":{"NO_1":32,"Folio":"2v","Top_Orig":"Afigeira","Lat_Orig":"41º30","Long_Orig":"1º27","Álvaro_Se":"--","Top_SD":"Azenha da Fonte Figueira","Lat_SD":"40º52","Long_SD":"8º35","Top_Atual":"Azenha da Fonte Figueira","Obs_VDigit":"","Distrito":"Aveiro","Concelho":"Ovar","Freguesia":"São João"}},
{"type":"Feature","geometry":{"type":"Point","coordinates":[-8.585674170272192,40.82193399410915]},"properties":{"NO_1":605,"Folio":"21","Top_Orig":"Daguarei","Lat_Orig":"41º27","Long_Orig":"1º23,33","Álvaro_Se":"VI,52","Top_SD":"Degarei","Lat_SD":"40º50","Long_SD":"8º34","Top_Atual":"S. João de Válega","Obs_VDigit":"Localizado através da cronologia da capela de S. João Batista, descrita no Sistema de Informação para o Património Arquitectónico","Distrito":"Aveiro","Concelho":"Ovar","Freguesia":"Válega"}},
{"type":"Feature","geometry":{"type":"Point","coordinates":[-8.625409143365994,40.85954161278546]},"properties":{"NO_1":986,"Folio":"33","Top_Orig":"Ouar","Lat_Orig":"41º30","Long_Orig":"1º23,33","Álvaro_Se":"VII,6","Top_SD":"Ovar","Lat_SD":"40º51","Long_SD":"8º37","Top_Atual":"Ovar","Obs_VDigit":"","Distrito":"Aveiro","Concelho":"Ovar","Freguesia":"Ovar"}},
{"type":"Feature","geometry":{"type":"Point","coordinates":[-8.477264277663688,40.840369708369074]},"properties":{"NO_1":984,"Folio":"33","Top_Orig":"Olyueiradazemeis","Lat_Orig":"41º24","Long_Orig":"1º27,5","Álvaro_Se":"VII,8","Top_SD":"Oliveira de Azeméis","Lat_SD":"40º50","Long_SD":"8º28","Top_Atual":"Oliveira de Azeméis","Obs_VDigit":"","Distrito":"Aveiro","Concelho":"Oliveira de Azeméis","Freguesia":"Oliveira de Azeméis"}},
{"type":"Feature","geometry":{"type":"Point","coordinates":[-8.43086107908554,40.8277234002404]},"properties":{"NO_1":985,"Folio":"33","Top_Orig":"OSela","Lat_Orig":"41º24","Long_Orig":"1º15","Álvaro_Se":"VII,11","Top_SD":"Ossela","Lat_SD":"40º49","Long_SD":"8º25","Top_Atual":"Ossela","Obs_VDigit":"","Distrito":"Aveiro","Concelho":"Oliveira de Azeméis","Freguesia":"Ossela"}},
{"type":"Feature","geometry":{"type":"Point","coordinates":[-8.652865060231543,40.74887226374247]},"properties":{"NO_1":1085,"Folio":"36","Top_Orig":"Pardelhas","Lat_Orig":"41º24","Long_Orig":"1º21","Álvaro_Se":"--","Top_SD":"Pardelhas","Lat_SD":"40º44","Long_SD":"8º39","Top_Atual":"Pardelhas","Obs_VDigit":"","Distrito":"Aveiro","Concelho":"Murtosa","Freguesia":"Murtosa"}},
{"type":"Feature","geometry":{"type":"Point","coordinates":[-8.635835747787963,40.73731349903272]},"properties":{"NO_1":827,"Folio":"28","Top_Orig":"MartoSa","Lat_Orig":"41º22","Long_Orig":"1º19,5","Álvaro_Se":"VII,4","Top_SD":"Murtosa","Lat_SD":"40º44","Long_SD":"8º38","Top_Atual":"Murtosa","Obs_VDigit":"","Distrito":"Aveiro","Concelho":"Murtosa","Freguesia":"Murtosa"}},
{"type":"Feature","geometry":{"type":"Point","coordinates":[-8.563499840857315,40.74982322594392]},"properties":{"NO_1":272,"Folio":"10","Top_Orig":"Amtoam","Lat_Orig":"41º21","Long_Orig":"1º21","Álvaro_Se":"--","Top_SD":"Antuã (Salreu)","Lat_SD":"40º44","Long_SD":"8º33","Top_Atual":"Antuã","Obs_VDigit":"","Distrito":"Aveiro","Concelho":"Estarreja","Freguesia":"Salreu"}},
{"type":"Feature","geometry":{"type":"Point","coordinates":[-8.478870491066605,40.69227855936216]},"properties":{"NO_1":333,"Folio":"12","Top_Orig":"Albergaria","Lat_Orig":"41º17,5","Long_Orig":"1º27","Álvaro_Se":"VII,10","Top_SD":"Albergaria-a-Velha","Lat_SD":"40º41","Long_SD":"8º29","Top_Atual":"Albergaria-a-Velha","Obs_VDigit":"","Distrito":"Aveiro","Concelho":"Albergaria-a-Velha","Freguesia":"Albergaria-a-Velha"}},
{"type":"Feature","geometry":{"type":"Point","coordinates":[-8.557205215005196,40.68026574106072]},"properties":{"NO_1":266,"Folio":"10","Top_Orig":"Amgeira","Lat_Orig":"41º18","Long_Orig":"1º18,75","Álvaro_Se":"VII,1","Top_SD":"Angeja","Lat_SD":"40º40","Long_SD":"8º33","Top_Atual":"Angeja","Obs_VDigit":"","Distrito":"Aveiro","Concelho":"Albergaria-a-Velha","Freguesia":"Angeja"}},
{"type":"Feature","geometry":{"type":"Point","coordinates":[-8.326403411477552,40.665202835752616]},"properties":{"NO_1":1036,"Folio":"34v","Top_Orig":"Pedrastalhadas","Lat_Orig":"41º12","Long_Orig":"1º34,5","Álvaro_Se":"IX,55","Top_SD":"Talhadas (Sever do Vouga)","Lat_SD":"40º39","Long_SD":"8º19","Top_Atual":"Talhadas","Obs_VDigit":"","Distrito":"Aveiro","Concelho":"Sever do Vouga","Freguesia":"Talhadas"}},
{"type":"Feature","geometry":{"type":"Point","coordinates":[-8.374420365902838,40.62430440538515]},"properties":{"NO_1":230,"Folio":"9","Top_Orig":"Adosfereiros","Lat_Orig":"41º10","Long_Orig":"1º32","Álvaro_Se":"IX,51","Top_SD":"A dos Ferreiros (Préstimo)","Lat_SD":"40º37","Long_SD":"8º22","Top_Atual":"A-dos-Ferreiros de Cima","Obs_VDigit":"","Distrito":"Aveiro","Concelho":"Águeda","Freguesia":"Préstimo"}},
{"type":"Feature","geometry":{"type":"Point","coordinates":[-8.42775425622543,40.521557995013126]},"properties":{"NO_1":232,"Folio":"9","Top_Orig":"Agoada","Lat_Orig":"41º02","Long_Orig":"1º19,5","Álvaro_Se":"IX,46","Top_SD":"Aguada de Cima","Lat_SD":"40º31","Long_SD":"8º25","Top_Atual":"Aguada de Cima","Obs_VDigit":"","Distrito":"Aveiro","Concelho":"Águeda","Freguesia":"Aguada de Cima"}},
{"type":"Feature","geometry":{"type":"Point","coordinates":[-8.469529162200677,40.53617263555421]},"properties":{"NO_1":409,"Folio":"14v","Top_Orig":"Baro","Lat_Orig":"41º03","Long_Orig":"1º23,33","Álvaro_Se":"IX,45","Top_SD":"Barrô","Lat_SD":"40º31","Long_SD":"8º28","Top_Atual":"Barrô","Obs_VDigit":"","Distrito":"Aveiro","Concelho":"Águeda","Freguesia":"Barrô"}},
{"type":"Feature","geometry":{"type":"Point","coordinates":[-8.492761916544232,40.51397135514463]},"properties":{"NO_1":968,"Folio":"32v","Top_Orig":"Oliueyra","Lat_Orig":"41º06","Long_Orig":"1º20","Álvaro_Se":"IX,39","Top_SD":"Oliveira do Bairro","Lat_SD":"40º30","Long_SD":"8º29","Top_Atual":"Oliveira do Bairro","Obs_VDigit":"","Distrito":"Aveiro","Concelho":"Oliveira do Bairro","Freguesia":"Oliveira do Bairro"}},
{"type":"Feature","geometry":{"type":"Point","coordinates":[-8.447303417323383,40.572623648322114]},"properties":{"NO_1":235,"Folio":"9","Top_Orig":"Ageda","Lat_Orig":"41º07,5","Long_Orig":"1º18","Álvaro_Se":"IX,47","Top_SD":"Agueda","Lat_SD":"40º34","Long_SD":"8º25","Top_Atual":"Agueda","Obs_VDigit":"","Distrito":"Aveiro","Concelho":"Águeda","Freguesia":"Águeda"}},
{"type":"Feature","geometry":{"type":"Point","coordinates":[-8.42639727954495,40.617161398265345]},"properties":{"NO_1":231,"Folio":"9","Top_Orig":"ARancada","Lat_Orig":"41º10","Long_Orig":"1º27,5","Álvaro_Se":"IX,50","Top_SD":"Arrancada (Valongo)","Lat_SD":"40º36","Long_SD":"8º25","Top_Atual":"Arrancada do Vouga","Obs_VDigit":"","Distrito":"Aveiro","Concelho":"Águeda","Freguesia":"Valongo do Vouga"}},
{"type":"Feature","geometry":{"type":"Point","coordinates":[-8.480677763575166,40.61071559736908]},"properties":{"NO_1":236,"Folio":"9","Top_Orig":"Atrofa","Lat_Orig":"41º10","Long_Orig":"1º23,33","Álvaro_Se":"IX,49","Top_SD":"Trofa do Vouga","Lat_SD":"40º37","Long_SD":"8º28","Top_Atual":"Trofa","Obs_VDigit":"","Distrito":"Aveiro","Concelho":"Águeda","Freguesia":"Trofa"}},
{"type":"Feature","geometry":{"type":"Point","coordinates":[-8.522679821656613,40.60796722143704]},"properties":{"NO_1":237,"Folio":"9","Top_Orig":"Almeala","Lat_Orig":"41º14","Long_Orig":"1º22","Álvaro_Se":"IX,48","Top_SD":"Almeara (Segadães)","Lat_SD":"40º36","Long_SD":"8º31","Top_Atual":"Almear","Obs_VDigit":"","Distrito":"Aveiro","Concelho":"Águeda","Freguesia":"Travassô"}},
{"type":"Feature","geometry":{"type":"Point","coordinates":[-8.538756061117184,40.543051285346124]},"properties":{"NO_1":969,"Folio":"32v","Top_Orig":"OJam","Lat_Orig":"41º06","Long_Orig":"1º18,75","Álvaro_Se":"--","Top_SD":"Oiã","Lat_SD":"40º32","Long_SD":"8º31","Top_Atual":"Oiã","Obs_VDigit":"","Distrito":"Aveiro","Concelho":"Oliveira do Bairro","Freguesia":"Oiã"}},
{"type":"Feature","geometry":{"type":"Point","coordinates":[-8.646704945260426,40.517560200564]},"properties":{"NO_1":970,"Folio":"32v","Top_Orig":"Ouca","Lat_Orig":"41º05","Long_Orig":"1º15","Álvaro_Se":"IX,24","Top_SD":"Ouca (Sôza)","Lat_SD":"40º31","Long_SD":"8º39","Top_Atual":"Ouca","Obs_VDigit":"","Distrito":"Aveiro","Concelho":"Vagos","Freguesia":"Ouca"}},
{"type":"Feature","geometry":{"type":"Point","coordinates":[-8.65780295243363,40.54430418265042]},"properties":{"NO_1":484,"Folio":"17","Top_Orig":"Coza","Lat_Orig":"41º06","Long_Orig":"1º15","Álvaro_Se":"IX,25","Top_SD":"Sôza (Vagos)","Lat_SD":"40º32","Long_SD":"8º39","Top_Atual":"Soza","Obs_VDigit":"","Distrito":"Aveiro","Concelho":"Vagos","Freguesia":"Sosa"}},
{"type":"Feature","geometry":{"type":"Point","coordinates":[-8.674838881791574,40.57880872842434]},"properties":{"NO_1":244,"Folio":"9v","Top_Orig":"Aermida","Lat_Orig":"41º07,5","Long_Orig":"1º15","Álvaro_Se":"IX,26","Top_SD":"Ermida (Ílhavo)","Lat_SD":"40º34","Long_SD":"8º39","Top_Atual":"Ermida","Obs_VDigit":"","Distrito":"Aveiro","Concelho":"Ílhavo","Freguesia":"Ílhavo (São Salvador)"}},
{"type":"Feature","geometry":{"type":"Point","coordinates":[-8.669775579278687,40.60043011782753]},"properties":{"NO_1":715,"Folio":"24v","Top_Orig":"Ilhauo","Lat_Orig":"41º10","Long_Orig":"1º15","Álvaro_Se":"IX,27","Top_SD":"Ílhavo","Lat_SD":"40º36","Long_SD":"8º39","Top_Atual":"Ílhavo","Obs_VDigit":"","Distrito":"Aveiro","Concelho":"Ílhavo","Freguesia":"Ílhavo (São Salvador)"}},
{"type":"Feature","geometry":{"type":"Point","coordinates":[-8.654466133624542,40.641855491000626]},"properties":{"NO_1":243,"Folio":"9v","Top_Orig":"AVeiro","Lat_Orig":"41º12,5","Long_Orig":"1º16,66","Álvaro_Se":"IX,28","Top_SD":"Aveiro","Lat_SD":"40º38","Long_SD":"8º39","Top_Atual":"Aveiro","Obs_VDigit":"","Distrito":"Aveiro","Concelho":"Aveiro","Freguesia":"Vera Cruz"}},
{"type":"Feature","geometry":{"type":"Point","coordinates":[-8.628120932866615,40.64900055813977]},"properties":{"NO_1":626,"Folio":"21v","Top_Orig":"ESgueira","Lat_Orig":"41º13,5","Long_Orig":"1º14","Álvaro_Se":"IX,29","Top_SD":"Esgueira","Lat_SD":"40º38","Long_SD":"8º37","Top_Atual":"Esgueira","Obs_VDigit":"","Distrito":"Aveiro","Concelho":"Aveiro","Freguesia":"Esgueira"}},
{"type":"Feature","geometry":{"type":"Point","coordinates":[-8.567677598252898,40.62927482508626]},"properties":{"NO_1":627,"Folio":"21v","Top_Orig":"EJxo","Lat_Orig":"41º15","Long_Orig":"1º21","Álvaro_Se":"IX,32","Top_SD":"Eixo (Aveiro)","Lat_SD":"40º37","Long_SD":"8º33","Top_Atual":"Eixo","Obs_VDigit":"","Distrito":"Aveiro","Concelho":"Aveiro","Freguesia":"Eixo"}},
{"type":"Feature","geometry":{"type":"Point","coordinates":[-8.529586667032946,40.61817836289624]},"properties":{"NO_1":1048,"Folio":"35","Top_Orig":"Pynheiro","Lat_Orig":"41º15","Long_Orig":"1º22,5","Álvaro_Se":"VII,7","Top_SD":"Pinheiro","Lat_SD":"40º37","Long_SD":"8º32","Top_Atual":"Pinheiro","Obs_VDigit":"","Distrito":"Aveiro","Concelho":"Albergaria-a-Velha","Freguesia":"São João de Loure"}},
{"type":"Feature","geometry":{"type":"Point","coordinates":[-8.537088368604655,40.65956957020306]},"properties":{"NO_1":665,"Folio":"23","Top_Orig":"Forroco","Lat_Orig":"41º17,5","Long_Orig":"1º21","Álvaro_Se":"VII,2","Top_SD":"Frossos","Lat_SD":"40º39","Long_SD":"8º31","Top_Atual":"Frossos","Obs_VDigit":"","Distrito":"Aveiro","Concelho":"Albergaria-a-Velha","Freguesia":"Frossos"}},
{"type":"Feature","geometry":{"type":"Point","coordinates":[-8.607232719869048,41.01921205823348]},"properties":{"NO_1":267,"Folio":"10","Top_Orig":"Abomça","Lat_Orig":"41º36","Long_Orig":"1º22,5","Álvaro_Se":"--","Top_SD":"Bouços (Guetim)","Lat_SD":"41º00","Long_SD":"8º36","Top_Atual":"Bouços","Obs_VDigit":"","Distrito":"Aveiro","Concelho":"Espinho","Freguesia":"Guetim"}},
{"type":"Feature","geometry":{"type":"Point","coordinates":[-8.511940631681938,41.0057296625775]},"properties":{"NO_1":987,"Folio":"33","Top_Orig":"Oterreyro","Lat_Orig":"41º33,75","Long_Orig":"1º34,5","Álvaro_Se":"--","Top_SD":"Terreiro (Sanguedo)","Lat_SD":"41º00","Long_SD":"8º30","Top_Atual":"Terreiro","Obs_VDigit":"","Distrito":"Aveiro","Concelho":"Santa Maria da Feira","Freguesia":"Sanguedo"}},
{"type":"Feature","geometry":{"type":"Point","coordinates":[-8.295663627646942,41.06506794857103]},"properties":{"NO_1":312,"Folio":"11v","Top_Orig":"AbalSa","Lat_Orig":"41º40","Long_Orig":"1º48,75","Álvaro_Se":"VII,34","Top_SD":"Balsa (Sardouro)","Lat_SD":"41º04","Long_SD":"8º17","Top_Atual":"Valsa","Obs_VDigit":"","Distrito":"Aveiro","Concelho":"Castelo de Paiva","Freguesia":"Santa Maria de Sardoura"}},
{"type":"Feature","geometry":{"type":"Point","coordinates":[-8.480925539354311,40.39838119381228]},"properties":{"NO_1":1486,"Folio":"49","Top_Orig":"Ventosa","Lat_Orig":"40º54","Long_Orig":"1º17,5","Álvaro_Se":"--","Top_SD":"Ventosa do Bairro","Lat_SD":"40º23","Long_SD":"8º28","Top_Atual":"Ventosa do Bairro","Obs_VDigit":"","Distrito":"Aveiro","Concelho":"Mealhada","Freguesia":"Ventosa do Bairro"}},
{"type":"Feature","geometry":{"type":"Point","coordinates":[-8.465387006010417,40.41614430170538]},"properties":{"NO_1":1357,"Folio":"45","Top_Orig":"Tamazegos","Lat_Orig":"40º56","Long_Orig":"1º21","Álvaro_Se":"--","Top_SD":"Tamengos (Anadia)","Lat_SD":"40º24","Long_SD":"8º27","Top_Atual":"Tamengos","Obs_VDigit":"","Distrito":"Aveiro","Concelho":"Anadia","Freguesia":"Tamengos"}},
{"type":"Feature","geometry":{"type":"Point","coordinates":[-8.398730028015011,40.40934657388465]},"properties":{"NO_1":1411,"Folio":"46v","Top_Orig":"Vylanoua","Lat_Orig":"40º54","Long_Orig":"1º24","Álvaro_Se":"--","Top_SD":"Vila Nova de Monsarrós","Lat_SD":"40º24","Long_SD":"8º23","Top_Atual":"Vila Nova de Monsarrós","Obs_VDigit":"","Distrito":"Aveiro","Concelho":"Anadia","Freguesia":"Vila Nova de Monsarros"}},
{"type":"Feature","geometry":{"type":"Point","coordinates":[-8.469346156743244,40.48615019469272]},"properties":{"NO_1":1289,"Folio":"42v","Top_Orig":"Samgalhos","Lat_Orig":"41º01","Long_Orig":"1º21","Álvaro_Se":"IX,38","Top_SD":"Sangalhos (Anadia)","Lat_SD":"40º29","Long_SD":"8º28","Top_Atual":"Sangalhos","Obs_VDigit":"","Distrito":"Aveiro","Concelho":"Anadia","Freguesia":"Sangalhos"}},
{"type":"Feature","geometry":{"type":"Point","coordinates":[-8.562164696596986,40.412646633438854]},"properties":{"NO_1":1359,"Folio":"45","Top_Orig":"ToResdoRyo","Lat_Orig":"40º56","Long_Orig":"1º15","Álvaro_Se":"IX,17","Top_SD":"Torres","Lat_SD":"40º24","Long_SD":"8º33","Top_Atual":"Torres","Obs_VDigit":"","Distrito":"Aveiro","Concelho":"Anadia","Freguesia":"Vilarinho do Bairro"}},
{"type":"Feature","geometry":{"type":"Point","coordinates":[-8.3073100279967,40.9346776538897]},"properties":{"NO_1":1326,"Folio":"44","Top_Orig":"Santamarinha","Lat_Orig":"41º30","Long_Orig":"1º43,5","Álvaro_Se":"VII,27","Top_SD":"Santa Marinha do Tropeço","Lat_SD":"40º56","Long_SD":"8º18","Top_Atual":"Tropeço","Obs_VDigit":"","Distrito":"Aveiro","Concelho":"Arouca","Freguesia":"Tropeço"}},
{"type":"Feature","geometry":{"type":"Point","coordinates":[-8.354837771056511,40.912684571098445]},"properties":{"NO_1":1167,"Folio":"39","Top_Orig":"Regodachaue","Lat_Orig":"41º22,5","Long_Orig":"1º32,5","Álvaro_Se":"VII,18","Top_SD":"Regada (Chave)","Lat_SD":"40º54","Long_SD":"8º21","Top_Atual":"Regada","Obs_VDigit":"","Distrito":"Aveiro","Concelho":"Arouca","Freguesia":"Chave"}},
{"type":"Feature","geometry":{"type":"Point","coordinates":[-8.133874235230627,40.87658694287143]},"properties":{"NO_1":1186,"Folio":"39v","Top_Orig":"Regoufen","Lat_Orig":"41º14","Long_Orig":"1º51","Álvaro_Se":"--","Top_SD":"Regoufe (Arouca)","Lat_SD":"40º52","Long_SD":"8º08","Top_Atual":"Regoufe","Obs_VDigit":"","Distrito":"Aveiro","Concelho":"Arouca","Freguesia":"Covelo de Paivó"}},
{"type":"Feature","geometry":{"type":"Point","coordinates":[-8.625694112176832,40.991385864620106]},"properties":{"NO_1":1265,"Folio":"42","Top_Orig":"Syluades","Lat_Orig":"41º33","Long_Orig":"1º30","Álvaro_Se":"VII,15","Top_SD":"Silvade (Espinho)","Lat_SD":"40º59","Long_SD":"8º37","Top_Atual":"Silvade","Obs_VDigit":"","Distrito":"Aveiro","Concelho":"Espinho","Freguesia":"Silvalde"}},
{"type":"Feature","geometry":{"type":"Point","coordinates":[-8.470627060861885,40.63946824001397]},"properties":{"NO_1":1501,"Folio":"49v","Top_Orig":"Vouga","Lat_Orig":"41º10","Long_Orig":"1º25","Álvaro_Se":"VII,9","Top_SD":"Vouga","Lat_SD":"40º38","Long_SD":"8º28","Top_Atual":"Vouga","Obs_VDigit":"","Distrito":"Aveiro","Concelho":"Águeda","Freguesia":"Lamas do Vouga"}},
{"type":"Feature","geometry":{"type":"Point","coordinates":[-8.529895639670588,40.59209029141839]},"properties":{"NO_1":1172,"Folio":"39","Top_Orig":"Requeixo","Lat_Orig":"41º12","Long_Orig":"1º21","Álvaro_Se":"IX,31","Top_SD":"Requeixo (Aveiro)","Lat_SD":"40º35","Long_SD":"8º31","Top_Atual":"Requeixo","Obs_VDigit":"","Distrito":"Aveiro","Concelho":"Aveiro","Freguesia":"Requeixo"}},
{"type":"Feature","geometry":{"type":"Point","coordinates":[-8.659176221060358,40.52442033017924]},"properties":{"NO_1":1521,"Folio":"50","Top_Orig":"Valdeperoco","Lat_Orig":"41º02","Long_Orig":"1º08","Álvaro_Se":"--","Top_SD":"Vale do Pereiro","Lat_SD":"40º31","Long_SD":"8º40","Top_Atual":"Vale do Pereiro","Obs_VDigit":"","Distrito":"Aveiro","Concelho":"Vagos","Freguesia":"Ouca"}},
{"type":"Feature","geometry":{"type":"Point","coordinates":[-8.681976511067118,40.55543697726006]},"properties":{"NO_1":1503,"Folio":"49v","Top_Orig":"Vagos","Lat_Orig":"41º06","Long_Orig":"1º13,33","Álvaro_Se":"IX,16","Top_SD":"Vagos","Lat_SD":"40º33","Long_SD":"8º40","Top_Atual":"Vagos","Obs_VDigit":"","Distrito":"Aveiro","Concelho":"Vagos","Freguesia":"Vagos"}},
{"type":"Feature","geometry":{"type":"Point","coordinates":[-8.60213986055772,40.58927581011886]},"properties":{"NO_1":1502,"Folio":"49v","Top_Orig":"Valade","Lat_Orig":"41º08","Long_Orig":"1º17,5","Álvaro_Se":"--","Top_SD":"Costa do Valado","Lat_SD":"40º35","Long_SD":"8º35","Top_Atual":"Costa do Valado","Obs_VDigit":"","Distrito":"Aveiro","Concelho":"Aveiro","Freguesia":"Oliveirinha"}},
{"type":"Feature","geometry":{"type":"Point","coordinates":[-8.735247481635497,40.64319165059598]},"properties":{"NO_1":1146,"Folio":"38","Top_Orig":"Pontedabara","Lat_Orig":"--","Long_Orig":"--","Álvaro_Se":"--","Top_SD":"Ponte da Barra","Lat_SD":"40º38","Long_SD":"8º43","Top_Atual":"Ponte da Barra","Obs_VDigit":"","Distrito":"Aveiro","Concelho":"Ílhavo","Freguesia":"Gafanha da Nazaré"}},
{"type":"Feature","geometry":{"type":"Point","coordinates":[-8.622673230741203,40.69040757202676]},"properties":{"NO_1":1414,"Folio":"46v","Top_Orig":"Vylarinho","Lat_Orig":"41º16,66","Long_Orig":"1º18","Álvaro_Se":"IX,30","Top_SD":"Vilarinho (Cacia)","Lat_SD":"40º41","Long_SD":"8º36","Top_Atual":"Vilarinho","Obs_VDigit":"","Distrito":"Aveiro","Concelho":"Aveiro","Freguesia":"Cacia"}},
{"type":"Feature","geometry":{"type":"Point","coordinates":[-8.54009902064215,40.632910414308064]},"properties":{"NO_1":1317,"Folio":"43v","Top_Orig":"Samyo","Lat_Orig":"41º16","Long_Orig":"1º21","Álvaro_Se":"VII,3","Top_SD":"São João de Loure","Lat_SD":"40º37","Long_SD":"8º31","Top_Atual":"São João de Loure","Obs_VDigit":"","Distrito":"Aveiro","Concelho":"Albergaria-a-Velha","Freguesia":"São João de Loure"}},
{"type":"Feature","geometry":{"type":"Point","coordinates":[-8.268080701774894,41.04307398684349]},"properties":{"NO_1":1253,"Folio":"41v","Top_Orig":"Sobrado","Lat_Orig":"41º36","Long_Orig":"1º50","Álvaro_Se":"VII,39","Top_SD":"Sobrado (Castelo de Paiva)","Lat_SD":"41º02","Long_SD":"8º15","Top_Atual":"Sobrado de Paiva","Obs_VDigit":"","Distrito":"Aveiro","Concelho":"Castelo de Paiva","Freguesia":"Sobrado"}}
]}